[{"word":"ز","pos":"character","pos_title":"Tîp","glosses":["Tîpeke alfabeya kurdî ya erebî û hevdengî z ya alfabeya kurdî ya latînî ye."]},{"word":"زاخان","pos":"adj","pos_title":"Rengdêr","glosses":["rêya dijwar, rêya sext, rêya asê"]},{"word":"زار","pos":"noun","pos_title":"Navdêr","glosses":["dev"],"synonyms":["دەم"]},{"word":"زازاکی","pos":"noun","pos_title":"Navdêr","glosses":["zazakî"]},{"word":"زازاکی","pos":"adj","pos_title":"Rengdêr","glosses":["zazakî"]},{"word":"زام","pos":"noun","pos_title":"Navdêr","glosses":["birîn"],"synonyms":["برین","ناسۆر"]},{"word":"زانکۆ","pos":"noun","pos_title":"Navdêr","glosses":["zanîngeh"]},{"word":"زاوا","pos":"noun","pos_title":"Navdêr","glosses":["zava"]},{"word":"زاڵ","pos":"adj","pos_title":"Rengdêr","glosses":["zal, serwer"]},{"word":"زاڵوو","pos":"noun","pos_title":"Navdêr","glosses":["Guhartoyeke زەروو (zerû)."]},{"word":"زبڵ","pos":"noun","pos_title":"Navdêr","glosses":["zibil"]},{"word":"زراو","pos":"noun","pos_title":"Navdêr","glosses":["zirav"]},{"word":"زراو بردن","pos":"verb","pos_title":"Lêker","glosses":["ziravê (yekî) qetandin, qudûmê (yekî) şkandin"]},{"word":"زراو تەقین","pos":"verb","pos_title":"Lêker","glosses":["ziravê (yekî) qetîn, qudûmê (yekî) şkestin"],"synonyms":["زراو ڕژان","زراو چوون"]},{"word":"زراو چوون","pos":"verb","pos_title":"Lêker","glosses":["ziravê (yekî) qetîn, qudûmê (yekî) şkestin"],"synonyms":["زراو ڕژان","زراو تەقین"]},{"word":"زراو ڕژان","pos":"verb","pos_title":"Lêker","glosses":["ziravê (yekî) qetîn, qudûmê (yekî) şkestin"],"synonyms":["زراو چوون","زراو تەقین"]},{"word":"زریان","pos":"noun","pos_title":"Navdêr","glosses":["bayê pir xurt, bahoz"]},{"word":"زریزە","pos":"noun","pos_title":"Navdêr","glosses":["Zincîrek e ku pir zirav be."]},{"word":"زرینگان","pos":"verb","pos_title":"Lêker","glosses":["çingînî kirin, zingandin"]},{"word":"زریکاندن","pos":"verb","pos_title":"Lêker","glosses":["qîjîn"],"synonyms":["قیژاندن"]},{"word":"زرێ","pos":"noun","pos_title":"Navdêr","glosses":["zirx","Guhartoyeke زەریا (zerya)."]},{"word":"زستان","pos":"noun","pos_title":"Navdêr","glosses":["zivistan"]},{"word":"زل","pos":"adj","pos_title":"Rengdêr","glosses":["dirêj û stûr","mezin"],"synonyms":["گەورە"]},{"word":"زللە","pos":"noun","pos_title":"Navdêr","glosses":["zel, sîle, şemaq"]},{"word":"زمان","pos":"noun","pos_title":"Navdêr","glosses":["ziman"]},{"word":"زمانشڕ","pos":"adj","pos_title":"Rengdêr","glosses":["zimandirêj, lewçe, çenebaz"],"synonyms":["هەرزەبێژ"]},{"word":"زمزق","pos":"noun","pos_title":"Navdêr","glosses":["boks kirin"]},{"word":"زنج","pos":"noun","pos_title":"Navdêr","glosses":["holik"]},{"word":"زوو","pos":"adj","pos_title":"Rengdêr","glosses":["zû"]},{"word":"زووخ","pos":"noun","pos_title":"Navdêr","glosses":["kêm, nêm, zox"],"synonyms":["زووخاو","کێم","هەو"]},{"word":"زووخاو","pos":"noun","pos_title":"Navdêr","glosses":["kêm, nêm, zox"],"synonyms":["زووخ","کێم","هەو"]},{"word":"زویر","pos":"adj","pos_title":"Rengdêr","glosses":["zivêr, bêzar, aciz"],"synonyms":["پەست"]},{"word":"زڕ","pos":"adj","pos_title":"Rengdêr","glosses":["bêber"]},{"word":"زڕخەو بوون","pos":"verb","pos_title":"Lêker","glosses":["xew lê herimîn, xew lê tewirîn"],"synonyms":["خەو زڕان"]},{"word":"زڕخەو کردن","pos":"verb","pos_title":"Lêker","glosses":["xew lê herimandin, xew lê tewirandin"],"synonyms":["خەو زڕاندن"]},{"word":"زڕە","pos":"noun","pos_title":"Navdêr","glosses":["zingîn"]},{"word":"زک","pos":"noun","pos_title":"Navdêr","glosses":["Guhartoyeke سک (sik)."]},{"word":"زگ","pos":"noun","pos_title":"Navdêr","glosses":["Guhartoyeke سک (sik)."]},{"word":"زگ پێ سووتان","pos":"verb","pos_title":"Lêker","glosses":["dil pê şewitîn, guneh pê hatin"],"synonyms":["بەزەیی پێدا هاتنەوە"]},{"word":"زگپڕ","pos":"adj","pos_title":"Rengdêr","glosses":["Guhartoyeke سکپڕ (sikpirr)."]},{"word":"زۆخ","pos":"noun","pos_title":"Navdêr","glosses":["Guhartoyeke زووخ (zûx)."]},{"word":"زۆر","pos":"adv","pos_title":"Hoker","glosses":["pirr, gelek, mişe, zaf, zehf"]},{"word":"زۆرینە","pos":"noun","pos_title":"Navdêr","glosses":["piranî"]},{"word":"زۆم","pos":"noun","pos_title":"Navdêr","glosses":["Guhartoyeke زۆمە (zome)."]},{"word":"زۆمە","pos":"noun","pos_title":"Navdêr","glosses":["Zom, cîyê ko kon lê tên vedan."],"synonyms":["هۆبە"]},{"word":"زیان","pos":"noun","pos_title":"Navdêr","glosses":["ziyan, zerar, xesar"]},{"word":"زیت","pos":"adj","pos_title":"Rengdêr","glosses":["hişyar, baldar"],"synonyms":["وریا"]},{"word":"زیتەڵ","pos":"adj","pos_title":"Rengdêr","glosses":["Guhartoyeke زیت (zît)."]},{"word":"زیندوو","pos":"noun","pos_title":"Navdêr","glosses":["candar, jîndar"],"synonyms":["گییانەوەر","گییاندار","گییانلەبەر"]},{"word":"زیندوو","pos":"adj","pos_title":"Rengdêr","glosses":["zindî, sax"]},{"word":"زیو","pos":"noun","pos_title":"Navdêr","glosses":["zîv"]},{"word":"زیوین","pos":"adj","pos_title":"Rengdêr","glosses":["zîvîn"]},{"word":"زیپکە","pos":"noun","pos_title":"Navdêr","glosses":["pizik"],"synonyms":["تامیسک"]},{"word":"زێ","pos":"noun","pos_title":"Navdêr","glosses":["zê, robar, şet"]},{"word":"زێد","pos":"noun","pos_title":"Navdêr","glosses":["nîştiman, welat","Ciyê jidayikbûnê."],"synonyms":["وڵات","نیشتمان","مەوتەن"]},{"word":"زێروو","pos":"noun","pos_title":"Navdêr","glosses":["Guhartoyeke زەروو (zerû)."]},{"word":"زێڕ","pos":"noun","pos_title":"Navdêr","glosses":["zêr"]},{"word":"زێڕکفت","pos":"adj","pos_title":"Rengdêr","glosses":["zêravî"]},{"word":"زەبەن","pos":"noun","pos_title":"Navdêr","glosses":["mêrg"],"synonyms":["بژوێن"]},{"word":"زەبەند","pos":"noun","pos_title":"Navdêr","glosses":["Guhartoyeke زەبەن (zeben)."]},{"word":"زەبەنگ","pos":"noun","pos_title":"Navdêr","glosses":["Guhartoyeke زەبەن (zeben)."]},{"word":"زەرد","pos":"noun","pos_title":"Navdêr","glosses":["zer"]},{"word":"زەرد","pos":"adj","pos_title":"Rengdêr","glosses":["zer"]},{"word":"زەردوو","pos":"noun","pos_title":"Navdêr","glosses":["Guhartoyeke زەروو (zerû)."]},{"word":"زەردەخەنە","pos":"noun","pos_title":"Navdêr","glosses":["girnij, bişir"],"synonyms":["خەنە","بزە"]},{"word":"زەردەواڵە","pos":"noun","pos_title":"Navdêr","glosses":["zirkêtk, mozqirtik"]},{"word":"زەردەپەڕ","pos":"noun","pos_title":"Navdêr","glosses":["tavzerk, elind, gizing, şefeq"],"synonyms":["گزنگ"]},{"word":"زەروو","pos":"noun","pos_title":"Navdêr","glosses":["zelû"]},{"word":"زەل","pos":"noun","pos_title":"Navdêr","glosses":["zil, qamîş, çîx, rûl"],"synonyms":["قامیش","چیت"]},{"word":"زەلکاو","pos":"noun","pos_title":"Navdêr","glosses":["avzê, lîtav"]},{"word":"زەمەن","pos":"noun","pos_title":"Navdêr","glosses":["Guhartoyeke زەبەن (zeben)."]},{"word":"زەمەند","pos":"noun","pos_title":"Navdêr","glosses":["Guhartoyeke زەبەن (zeben)."]},{"word":"زەندۆر","pos":"noun","pos_title":"Navdêr","glosses":["Qelşa dirêj û stûr a di nav axê de."],"synonyms":["ڕەهۆڵ","بوودڕ"]},{"word":"زەندۆڵ","pos":"noun","pos_title":"Navdêr","glosses":["Guhartoyeke زەندۆر (zendor)."]},{"word":"زەنگ","pos":"noun","pos_title":"Navdêr","glosses":["zengil"]},{"word":"زەنگوڵ","pos":"noun","pos_title":"Navdêr","glosses":["dilop, niqut, çipik"],"synonyms":["چۆڕ","دڵۆپ","تنۆک"]},{"word":"زەنگیانە","pos":"noun","pos_title":"Navdêr","glosses":["Cûnekî moriyan e ku hûrik û rengîn in."]},{"word":"زەوی","pos":"noun","pos_title":"Navdêr","glosses":["erd","zevî"]},{"word":"زەڕاندن","pos":"verb","pos_title":"Lêker","glosses":["zirrîn"]},{"word":"زەڕنەقووتە","pos":"noun","pos_title":"Navdêr","glosses":["Çêlikên çivîkan ên ku hîn naşên bifirin û di nav hêlînê de dihewin."]},{"word":"زەڕەبین","pos":"noun","pos_title":"Navdêr","glosses":["mercek, girdok"],"synonyms":["گەردبین"]},{"word":"زەیتوون","pos":"noun","pos_title":"Navdêr","glosses":["zeytûn"]}]